unpack_recursive/__init__.py
unpack_recursive/console_app.py
unpack_recursive/patool_unpack/__init__.py
unpack_recursive/patool_unpack/configuration.py
unpack_recursive/patool_unpack/util.py
unpack_recursive/patool_unpack/programs/__init__.py
unpack_recursive/patool_unpack/programs/ar.py
unpack_recursive/patool_unpack/programs/arc.py
unpack_recursive/patool_unpack/programs/archmage.py
unpack_recursive/patool_unpack/programs/arj.py
unpack_recursive/patool_unpack/programs/bsdcpio.py
unpack_recursive/patool_unpack/programs/bsdtar.py
unpack_recursive/patool_unpack/programs/bzip2.py
unpack_recursive/patool_unpack/programs/cabextract.py
unpack_recursive/patool_unpack/programs/chmlib.py
unpack_recursive/patool_unpack/programs/clzip.py
unpack_recursive/patool_unpack/programs/compress.py
unpack_recursive/patool_unpack/programs/cpio.py
unpack_recursive/patool_unpack/programs/dpkg.py
unpack_recursive/patool_unpack/programs/flac.py
unpack_recursive/patool_unpack/programs/genisoimage.py
unpack_recursive/patool_unpack/programs/gzip.py
unpack_recursive/patool_unpack/programs/isoinfo.py
unpack_recursive/patool_unpack/programs/lbzip2.py
unpack_recursive/patool_unpack/programs/lcab.py
unpack_recursive/patool_unpack/programs/lha.py
unpack_recursive/patool_unpack/programs/lhasa.py
unpack_recursive/patool_unpack/programs/lrzip.py
unpack_recursive/patool_unpack/programs/lzip.py
unpack_recursive/patool_unpack/programs/lzma.py
unpack_recursive/patool_unpack/programs/lzop.py
unpack_recursive/patool_unpack/programs/mac.py
unpack_recursive/patool_unpack/programs/nomarch.py
unpack_recursive/patool_unpack/programs/p7azip.py
unpack_recursive/patool_unpack/programs/p7rzip.py
unpack_recursive/patool_unpack/programs/p7zip.py
unpack_recursive/patool_unpack/programs/pbzip2.py
unpack_recursive/patool_unpack/programs/pdlzip.py
unpack_recursive/patool_unpack/programs/pigz.py
unpack_recursive/patool_unpack/programs/plzip.py
unpack_recursive/patool_unpack/programs/py_bz2.py
unpack_recursive-1.1.0.dist-info/LICENSE
unpack_recursive-1.1.0.dist-info/METADATA
unpack_recursive-1.1.0.dist-info/WHEEL
unpack_recursive-1.1.0.dist-info/entry_points.txt
unpack_recursive-1.1.0.dist-info/top_level.txt
unpack_recursive-1.1.0.dist-info/RECORD
