Metadata-Version: 2.1
Name: unpack-recursive
Version: 1.1.0
Summary: Recursive unpacking any type of archives
Home-page: https://github.com/Theodikes/unpack-recursive
Author: Theodike
Author-email: gvedichi@gmail.com
License: UNKNOWN
Keywords: recursive,unpack archive,unzip recursive,unpack recursive
Platform: UNKNOWN
Classifier: Programming Language :: Python
Classifier: Programming Language :: Python :: 3.6
Classifier: Programming Language :: Python :: 3.7
Classifier: Programming Language :: Python :: 3.8
Classifier: Programming Language :: Python :: 3.9
Classifier: Programming Language :: Python :: 3.10
Classifier: License :: OSI Approved :: GNU General Public License v3 (GPLv3)
Classifier: Operating System :: OS Independent
Requires-Python: >=3.6
License-File: LICENSE
Requires-Dist: typing-extensions
